oneNeuron/__init__.py
oneNeuron/perceptron.py
python_packaging_dl_sidh1603-0.0.3.dist-info/LICENSE
python_packaging_dl_sidh1603-0.0.3.dist-info/METADATA
python_packaging_dl_sidh1603-0.0.3.dist-info/WHEEL
python_packaging_dl_sidh1603-0.0.3.dist-info/top_level.txt
python_packaging_dl_sidh1603-0.0.3.dist-info/RECORD
