Metadata-Version: 2.1
Name: python-packaging-dl-sidh1603
Version: 0.0.3
Summary: A small package for perceptron
Home-page: https://github.com/sidh1603/python_packaging_dl
Author: sidh1603
Author-email: sidhu.rana34@gmail.com
Project-URL: Bug Tracker, https://github.com/sidh1603/python_packaging_dl/issues
Classifier: Programming Language :: Python :: 3
Classifier: License :: OSI Approved :: MIT License
Classifier: Operating System :: OS Independent
Requires-Python: >=3.6
License-File: LICENSE
Requires-Dist: numpy (==1.21.4)
Requires-Dist: pandas (==1.3.4)
Requires-Dist: joblib (==1.1.0)
